aws_ml_helper/__init__.py
aws_ml_helper/__main__.py
aws_ml_helper/boto.py
aws_ml_helper/commands.py
aws_ml_helper/config.py
aws_ml_helper/instance.py
aws_ml_helper/spot.py
aws_ml_helper/vpc.py
aws_ml_helper-0.0.0.dist-info/DESCRIPTION.rst
aws_ml_helper-0.0.0.dist-info/METADATA
aws_ml_helper-0.0.0.dist-info/RECORD
aws_ml_helper-0.0.0.dist-info/WHEEL
aws_ml_helper-0.0.0.dist-info/entry_points.txt
aws_ml_helper-0.0.0.dist-info/metadata.json
aws_ml_helper-0.0.0.dist-info/top_level.txt
