Metadata-Version: 2.0
Name: aws-ml-helper
Version: 0.0.0
Summary: AWS Helper for Machine Learning
Home-page: https://github.com/alefnula/aws-ml-helper
Author: Viktor Kerkez
Author-email: alefnula@gmail.com
License: BSD
Platform: Windows
Platform: POSIX
Platform: MacOSX
Requires-Dist: click (==6.7)
Requires-Dist: boto3 (==1.6.6)
Requires-Dist: paramiko (==2.4.0)
